aldryn_people/__init__.py
aldryn_people/admin.py
aldryn_people/apps.py
aldryn_people/cms_apps.py
aldryn_people/cms_plugins.py
aldryn_people/cms_toolbars.py
aldryn_people/cms_wizards.py
aldryn_people/menu.py
aldryn_people/models.py
aldryn_people/search_indexes.py
aldryn_people/urls.py
aldryn_people/utils.py
aldryn_people/vcard.py
aldryn_people/views.py
aldryn_people/boilerplates/bootstrap3/templates/aldryn_people/base.html
aldryn_people/boilerplates/bootstrap3/templates/aldryn_people/fullwidth.html
aldryn_people/boilerplates/bootstrap3/templates/aldryn_people/group_detail.html
aldryn_people/boilerplates/bootstrap3/templates/aldryn_people/group_list.html
aldryn_people/boilerplates/bootstrap3/templates/aldryn_people/person_detail.html
aldryn_people/boilerplates/bootstrap3/templates/aldryn_people/includes/group.html
aldryn_people/boilerplates/bootstrap3/templates/aldryn_people/includes/person.html
aldryn_people/boilerplates/bootstrap3/templates/aldryn_people/plugins/feature/people_list.html
aldryn_people/boilerplates/bootstrap3/templates/aldryn_people/plugins/standard/people_list.html
aldryn_people/boilerplates/legacy/templates/aldryn_people/group_detail.html
aldryn_people/boilerplates/legacy/templates/aldryn_people/group_list.html
aldryn_people/boilerplates/legacy/templates/aldryn_people/person_detail.html
aldryn_people/boilerplates/legacy/templates/aldryn_people/includes/people_item.html
aldryn_people/boilerplates/legacy/templates/aldryn_people/includes/people_items.html
aldryn_people/boilerplates/legacy/templates/aldryn_people/plugins/people_list.html
aldryn_people/boilerplates/legacy/templates/aldryn_people/plugins/feature/people_list.html
aldryn_people/boilerplates/legacy/templates/aldryn_people/plugins/standard/people_list.html
aldryn_people/locale/de/LC_MESSAGES/django.mo
aldryn_people/locale/de/LC_MESSAGES/django.po
aldryn_people/locale/en/LC_MESSAGES/django.mo
aldryn_people/locale/en/LC_MESSAGES/django.po
aldryn_people/locale/es/LC_MESSAGES/django.mo
djangocms_aldryn_people-3.0.2.dist-info/LICENSE.txt
djangocms_aldryn_people-3.0.2.dist-info/METADATA
djangocms_aldryn_people-3.0.2.dist-info/WHEEL
djangocms_aldryn_people-3.0.2.dist-info/top_level.txt
djangocms_aldryn_people-3.0.2.dist-info/RECORD
