Metadata-Version: 2.1
Name: djangocms-aldryn-people
Version: 3.0.2
Summary: Aldryn People publishes profile pages for people in your organisation including team members, collaborators, partners, clients, and so on, including photographs and address information.
Home-page: https://github.com/CZ-NIC/djangocms-aldryn-people
Author: Divio AG
Author-email: info@divio.ch
License: BSD
Platform: OS Independent
Classifier: Development Status :: 5 - Production/Stable
Classifier: Environment :: Web Environment
Classifier: Framework :: Django
Classifier: Framework :: Django :: 3.2
Classifier: Framework :: Django :: 4.0
Classifier: Intended Audience :: Developers
Classifier: License :: OSI Approved :: BSD License
Classifier: Operating System :: OS Independent
Classifier: Programming Language :: Python
Classifier: Programming Language :: Python :: 3.7
Classifier: Programming Language :: Python :: 3.8
Classifier: Programming Language :: Python :: 3.9
Classifier: Programming Language :: Python :: 3.10
Classifier: Topic :: Internet :: WWW/HTTP :: Dynamic Content
Classifier: Topic :: Software Development
Classifier: Topic :: Software Development :: Libraries :: Application Frameworks
Requires-Python: >=3.7
License-File: LICENSE.txt
Requires-Dist: djangocms-aldryn-common
Requires-Dist: djangocms-aldryn-translation-tools
Requires-Dist: djangocms-aldryn-search
Requires-Dist: django-filer
Requires-Dist: easy-thumbnails[svg]
Requires-Dist: phonenumbers
